CHANGES.txt
LICENSE.txt
Makefile
README.txt
header.txt
setup.py
version.txt
src/__init__.py
src/haufe/__init__.py
src/haufe.selenium.egg-info/PKG-INFO
src/haufe.selenium.egg-info/SOURCES.txt
src/haufe.selenium.egg-info/dependency_links.txt
src/haufe.selenium.egg-info/entry_points.txt
src/haufe.selenium.egg-info/namespace_packages.txt
src/haufe.selenium.egg-info/not-zip-safe
src/haufe.selenium.egg-info/requires.txt
src/haufe.selenium.egg-info/top_level.txt
src/haufe/selenium/__init__.py
src/haufe/selenium/cli.py
src/haufe/selenium/selenium-server.jar
src/haufe/selenium/testing/__init__.py
src/haufe/selenium/testing/selenium.py
src/haufe/selenium/testing/testcase.py
src/haufe/selenium/tests/__init__.py
src/haufe/selenium/tests/testSimple.py