Metadata-Version: 1.0
Name: haufe.selenium
Version: 0.3.0
Summary: A Python wrapper for controlling the Selenium Remote Server
Home-page: http://pypi.python.org/pypi/haufe.selenium
Author: Andreas Jung
Author-email: list@zopyx.com
License: LGPL 2.1
Platform: UNKNOWN
Classifier: Programming Language :: Python
Classifier: Environment :: Web Environment
